hpogrid/__init__.py
hpogrid/_version.py
hpogrid/decorators.py
hpogrid/algorithms/__init__.py
hpogrid/algorithms/ax_algorithm.py
hpogrid/algorithms/base_algorithm.py
hpogrid/algorithms/bohb_algorithm.py
hpogrid/algorithms/hyperopt_algorithm.py
hpogrid/algorithms/nevergrad_algorithm.py
hpogrid/algorithms/optuna_algorithm.py
hpogrid/algorithms/skopt_algorithm.py
hpogrid/clis/__init__.py
hpogrid/clis/configuration.py
hpogrid/clis/core.py
hpogrid/clis/tasks.py
hpogrid/components/__init__.py
hpogrid/components/abstract_object.py
hpogrid/components/grid_handler.py
hpogrid/components/grid_site_info.py
hpogrid/components/hpo_report.py
hpogrid/components/hpo_task.py
hpogrid/components/validation.py
hpogrid/configuration/__init__.py
hpogrid/configuration/configuration_base.py
hpogrid/configuration/grid_configuration.py
hpogrid/configuration/hpo_configuration.py
hpogrid/configuration/model_configuration.py
hpogrid/configuration/project_configuration.py
hpogrid/configuration/search_space_configuration.py
hpogrid/core/__init__.py
hpogrid/core/config_manager.py
hpogrid/core/decorators.py
hpogrid/core/defaults.py
hpogrid/core/environment_settings.py
hpogrid/future/__init__.py
hpogrid/future/rucio.py
hpogrid/generators/__init__.py
hpogrid/generators/ax_generator.py
hpogrid/generators/base_generator.py
hpogrid/generators/bohb_generator.py
hpogrid/generators/grid_generator.py
hpogrid/generators/hyperopt_generator.py
hpogrid/generators/nevergrad_generator.py
hpogrid/generators/optuna_generator.py
hpogrid/generators/skopt_generator.py
hpogrid/interface/__init__.py
hpogrid/interface/idds/__init__.py
hpogrid/interface/idds/main.py
hpogrid/interface/idds/steering.py
hpogrid/interface/panda/__init__.py
hpogrid/interface/panda/panda_task_manager.py
hpogrid/interface/panda/panda_task_report.py
hpogrid/interface/tune/__init__.py
hpogrid/interface/tune/callbacks.py
hpogrid/interface/tune/wrappers.py
hpogrid/resources/idds.cfg
hpogrid/schedulers/__init__.py
hpogrid-1.3.3.dist-info/LICENSE
hpogrid-1.3.3.dist-info/METADATA
hpogrid-1.3.3.dist-info/WHEEL
hpogrid-1.3.3.dist-info/top_level.txt
hpogrid-1.3.3.dist-info/RECORD
