Metadata-Version: 2.1
Name: hpogrid
Version: 1.3.3
Summary: A workflow for hyperparamter optimization using the ATLAS grid resources
Home-page: https://gitlab.cern.ch/aml/hyperparameter-optimization/alkaid-qt/hpogrid
Author: Alkaid Cheng
Author-email: chi.lung.cheng@cern.ch
Classifier: Programming Language :: Python :: 3.6
Classifier: Programming Language :: Python :: 3.7
Classifier: Programming Language :: Python :: 3.8
Classifier: License :: OSI Approved :: MIT License
Classifier: Operating System :: OS Independent
Requires-Python: >=3.6
License-File: LICENSE
Requires-Dist: pandas
Requires-Dist: tqdm
Requires-Dist: click
Requires-Dist: tabulate
Requires-Dist: numpy
Requires-Dist: psutil
